{
  "project_info": {
    "project_number": "62806150954",
    "firebase_url": "https://shortcutcalculator.firebaseio.com",
    "project_id": "shortcutcalculator",
    "storage_bucket": "shortcutcalculator.appspot.com"
  },
  "client": [
    {
      "client_info": {
        "mobilesdk_app_id": "1:62806150954:android:686c0bfd0f7b7100",
        "android_client_info": {
          "package_name": "com.brmuncey.shortcutcalculator"
        }
      },
      "oauth_client": [
        {
          "client_id": "62806150954-49aknobpl03op2q77mp3mgv3snenp2sk.apps.googleusercontent.com",
          "client_type": 1,
          "android_info": {
            "package_name": "com.brmuncey.shortcutcalculator",
            "certificate_hash": "8c04189ac4105adf31232e2605bbe25a0f11d249"
          }
        },
        {
          "client_id": "62806150954-fkpnrufrdcopaeiedslo7oa77v094j1q.apps.googleusercontent.com",
          "client_type": 3
        }
      ],
      "api_key": [
        {
          "current_key": "AIzaSyDnuMZmKmVQ9LzL0hpZKBGDOcLZ24U5CTg"
        },
        {
          "current_key": "AIzaSyDNNiBgIWAcxiOwkYrTOQWHW1Kj0g6Ur6Y"
        }
      ],
      "services": {
        "analytics_service": {
          "status": 1
        },
        "appinvite_service": {
          "status": 2,
          "other_platform_oauth_client": [
            {
              "client_id": "62806150954-fkpnrufrdcopaeiedslo7oa77v094j1q.apps.googleusercontent.com",
              "client_type": 3
            }
          ]
        },
        "ads_service": {
          "status": 2
        }
      }
    }
  ],
  "configuration_version": "1"
}